MANIFEST.in
README.md
requirements.txt
setup.py
tests-requirements.txt
my_little_ticket/__init__.py
my_little_ticket/local_settings.py
my_little_ticket/settings.py
my_little_ticket/tests_settings.py
my_little_ticket/urls.py
my_little_ticket/wsgi.py
my_little_ticket.egg-info/PKG-INFO
my_little_ticket.egg-info/SOURCES.txt
my_little_ticket.egg-info/dependency_links.txt
my_little_ticket.egg-info/requires.txt
my_little_ticket.egg-info/top_level.txt
my_little_ticket/plugins/__init__.py
my_little_ticket/plugins/base.py
my_little_ticket/plugins/default.py
my_little_ticket/plugins/jira.py
my_little_ticket/plugins/test_default.py
my_little_ticket/plugins/test_jira.py
my_little_ticket/tickets/__init__.py
my_little_ticket/tickets/admin.py
my_little_ticket/tickets/apps.py
my_little_ticket/tickets/metrics.py
my_little_ticket/tickets/models.py
my_little_ticket/tickets/serializers.py
my_little_ticket/tickets/tests.py
my_little_ticket/tickets/urls.py
my_little_ticket/tickets/views.py
my_little_ticket/tickets/management/__init__.py
my_little_ticket/tickets/management/commands/__init__.py
my_little_ticket/tickets/management/commands/tickets.py
my_little_ticket/tickets/migrations/0001_initial.py
my_little_ticket/tickets/migrations/0002_ticket_priority.py
my_little_ticket/tickets/migrations/__init__.py
my_little_ticket/tickets/static/favicon-danger.ico
my_little_ticket/tickets/static/favicon-idle.ico
my_little_ticket/tickets/static/favicon-info.ico
my_little_ticket/tickets/static/favicon-success.ico
my_little_ticket/tickets/static/favicon-warning.ico
my_little_ticket/tickets/static/favicon.ico
my_little_ticket/tickets/static/main.css
my_little_ticket/tickets/templates/base.html
my_little_ticket/tickets/templates/board.html
my_little_ticket/tickets/templates/bootstrap.html
my_little_ticket/tickets/templates/index.html
my_little_ticket/tickets/templatetags/__init__.py
my_little_ticket/tickets/templatetags/active.py